[
    {
        "id": "Encootech.AutomationActivity.CV.IndicateCVRegion",
        "name": "assign-cv-window.md",
        "localizedName": "指定CV窗口",
        "uuid": "11acb9ad-2005-472f-a2ad-3072e07f0614",
        "labels": "指定CV窗口，CV"
    },
    {
        "id": "Encootech.AutomationActivity.CV.CVClick",
        "name": "cv-click.md",
        "localizedName": "CV点击",
        "uuid": "543f8bc1-8b18-48d4-a3f4-240ada6cfa9c",
        "labels": "CV点击，CV"
    },
    {
        "id": "Encootech.AutomationActivity.CV.CVHover",
        "name": "cv-hover.md",
        "localizedName": "CV悬停",
        "uuid": "4c3069e6-e3b8-4fb6-baee-b380b8a10f6f",
        "labels": "CV悬停，CV"
    },
    {
        "id": "Encootech.AutomationActivity.CV.CVSetText",
        "name": "cv-input-text.md",
        "localizedName": "CV输入文本",
        "uuid": "b6769cea-d662-4d5a-97fe-3428ba2d4e74",
        "labels": "CV输入文本，CV"
    },
    {
        "id": "Encootech.AutomationActivity.CV.CVGetText",
        "name": "cv-get-text.md",
        "localizedName": "CV获取文本",
        "uuid": "ad14bf2d-16c0-499c-af20-cd525c515781",
        "labels": "CV获取文本，CV"
    },
    {
        "id": "Encootech.AutomationActivity.CV.CVSendHotKey",
        "name": "cv-send-shortcut.md",
        "localizedName": "CV发送快捷键",
        "uuid": "4eb66f44-33d4-4f8d-a639-f5f734de6b37",
        "labels": "CV发送快捷键，CV"
    },
    {
        "id": "Encootech.AutomationActivity.CV.CVWaitElementAppear",
        "name": "cv-wait-element-appear.md",
        "localizedName": "CV等待元素出现",
        "uuid": "84259835-4208-4073-9f44-bea015551d93",
        "labels": "CV等待元素出现，CV"
    },
    {
        "id": "Encootech.AutomationActivity.CV.CVWaitElementVanish",
        "name": "cv-wait-element-disappear.md",
        "localizedName": "CV等待元素消失",
        "uuid": "fffd1f3c-af59-44dc-aee9-fd35a2808765",
        "labels": "CV等待元素消失，CV"
    }
]