[
    {
        "id": null,
        "name": "DataTable",
        "localizedName": "数据表"
    },
    {
        "id": null,
        "name": "JSON",
        "localizedName": "JSON"
    },
    {
        "id": null,
        "name": "CollectionProcessing",
        "localizedName": "集合"
    },
    {
        "id": null,
        "name": "ArrayProcessing",
        "localizedName": "数组"
    },
    {
        "id": null,
        "name": "Dictionary",
        "localizedName": "字典"
    },
    {
        "id": null,
        "name": "TypeConversion",
        "localizedName": "类型转换"
    },
    {
        "id": null,
        "name": "TextProcessing",
        "localizedName": "文本"
    },
    {
        "id": null,
        "name": "DataProcessing",
        "localizedName": "格式"
    },
    {
        "id": "BotTime.ActivityLibrary.Activities.System.Tool.SetPasswordActivity",
        "name": "SetPassword.md",
        "localizedName": "设置密码",
        "uuid": "2cc94c74-5623-4270-94be-b2dad5c2bcc7",
        "labels": "设置, 密码"
    },
    {
        "id": "BotTime.ActivityLibrary.Activities.System.Tool.SetDateActivity",
        "name": "SetDateTime.md",
        "localizedName": "设置日期和时间",
        "uuid": "0fccefc9-5de7-4d35-90fa-af3f46ef194b",
        "labels": "日期, 设置, 时间"
    },
    {
        "id": "BotTime.Flow.Activities.Assign",
        "name": "Assign.md",
        "localizedName": "赋值",
        "uuid": "f3357989-015c-4a1b-8087-d1fd90a8511b",
        "labels": "赋值"
    },
    {
        "id": "BotTime.Flow.Activities.MultipleAssign",
        "name": "MultipleAssign.md",
        "localizedName": "赋值(多个)",
        "uuid": "216356ac-79a8-4d9c-8907-b5bd24c36a07",
        "labels": "赋值, 多个"
    }
]