[
    {
        "id": "Encoo.CodeTool.Activity.PythonInstallActivity",
        "name": "PythonInstall.md",
        "localizedName": "安装Python",
        "uuid": "78030805-3727-4f62-b477-70c8501d8edd"
    },
    {
        "id": "Encoo.CodeTool.Activity.PythonScopeActivity",
        "name": "PythonScope.md",
        "localizedName": "Python环境",
        "uuid": "463bb7cb-1adf-4dd3-a242-3158dfd7af58"
    },
    {
        "id": "Encoo.CodeTool.Activity.PythonExecuteFileActivity",
        "name": "PythonExcuteFile.md",
        "localizedName": "执行Python代码",
        "uuid": "568dc641-15e0-41fc-a8ed-b2ac92f1e45b"
    }
]